GailvlunYuShulitongjiXitiCankaoJiedaXianYoudian/README.md
GailvlunYuShulitongjiXitiCankaoJiedaXianYoudian/__init__.py
GailvlunYuShulitongjiXitiCankaoJiedaXianYoudian/__main__.py
GailvlunYuShulitongjiXitiCankaoJiedaXianYoudian/file.pdf
GailvlunYuShulitongjiXitiCankaoJiedaXianYoudian/index.html
gailvlun_yu_shulitongji_xiti_cankao_jieda_xian_youdian-2024.3.2.0.dist-info/METADATA
gailvlun_yu_shulitongji_xiti_cankao_jieda_xian_youdian-2024.3.2.0.dist-info/WHEEL
gailvlun_yu_shulitongji_xiti_cankao_jieda_xian_youdian-2024.3.2.0.dist-info/entry_points.txt
gailvlun_yu_shulitongji_xiti_cankao_jieda_xian_youdian-2024.3.2.0.dist-info/top_level.txt
gailvlun_yu_shulitongji_xiti_cankao_jieda_xian_youdian-2024.3.2.0.dist-info/RECORD
